cobaya/__init__.py
cobaya/__main__.py
cobaya/bib.py
cobaya/collection.py
cobaya/component.py
cobaya/conventions.py
cobaya/doc.py
cobaya/functions.py
cobaya/input.py
cobaya/install.py
cobaya/likelihood.py
cobaya/log.py
cobaya/model.py
cobaya/mpi.py
cobaya/output.py
cobaya/parameterization.py
cobaya/post.py
cobaya/prior.py
cobaya/run.py
cobaya/sampler.py
cobaya/theory.py
cobaya/tools.py
cobaya/typing.py
cobaya/yaml.py
cobaya/cosmo_input/__init__.py
cobaya/cosmo_input/autoselect_covmat.py
cobaya/cosmo_input/convert_cosmomc.py
cobaya/cosmo_input/create_input.py
cobaya/cosmo_input/gui.py
cobaya/cosmo_input/input_database.py
cobaya/grid_tools/__init__.py
cobaya/grid_tools/batchjob.py
cobaya/grid_tools/batchjob_args.py
cobaya/grid_tools/conventions.py
cobaya/grid_tools/delete_jobs.py
cobaya/grid_tools/gridconfig.py
cobaya/grid_tools/gridmanage.py
cobaya/grid_tools/gridrun.py
cobaya/grid_tools/gridtables.py
cobaya/grid_tools/jobqueue.py
cobaya/grid_tools/runMPI.py
cobaya/grid_tools/running_jobs.py
cobaya/likelihoods/__init__.py
cobaya/likelihoods/H0/__init__.py
cobaya/likelihoods/H0/freedman2020.bibtex
cobaya/likelihoods/H0/freedman2020.py
cobaya/likelihoods/H0/freedman2020.yaml
cobaya/likelihoods/H0/riess2018a.bibtex
cobaya/likelihoods/H0/riess2018a.py
cobaya/likelihoods/H0/riess2018a.yaml
cobaya/likelihoods/H0/riess2018b.bibtex
cobaya/likelihoods/H0/riess2018b.py
cobaya/likelihoods/H0/riess2018b.yaml
cobaya/likelihoods/H0/riess201903.bibtex
cobaya/likelihoods/H0/riess201903.py
cobaya/likelihoods/H0/riess201903.yaml
cobaya/likelihoods/H0/riess2020.bibtex
cobaya/likelihoods/H0/riess2020.py
cobaya/likelihoods/H0/riess2020.yaml
cobaya/likelihoods/H0/riess2020Mb.py
cobaya/likelihoods/H0/riess2020Mb.yaml
cobaya/likelihoods/_test/__init__.py
cobaya/likelihoods/_test/_test.py
cobaya/likelihoods/_test/_test.yaml
cobaya/likelihoods/bao/__init__.py
cobaya/likelihoods/bao/desi_2024_bao.bibtex
cobaya/likelihoods/bao/desi_2024_bao_all.py
cobaya/likelihoods/bao/desi_2024_bao_all.yaml
cobaya-3.6.1.dist-info/licenses/LICENCE.txt
cobaya-3.6.1.dist-info/METADATA
cobaya-3.6.1.dist-info/WHEEL
cobaya-3.6.1.dist-info/entry_points.txt
cobaya-3.6.1.dist-info/top_level.txt
cobaya-3.6.1.dist-info/RECORD
