Metadata-Version: 2.4
Name: cobaya
Version: 3.6.1
Summary: Code for Bayesian Analysis
Author: Jesus Torrado, Antony Lewis
License-Expression: LGPL-3.0-or-later AND LicenseRef-GFDL-1.3-or-later
Project-URL: Homepage, https://cobaya.readthedocs.io
Project-URL: Documentation, https://cobaya.readthedocs.io
Project-URL: Source, https://github.com/CobayaSampler/cobaya
Project-URL: Tracker, https://github.com/CobayaSampler/cobaya/issues
Project-URL: Licensing, https://github.com/CobayaSampler/cobaya/blob/master/LICENCE.txt
Keywords: montecarlo,sampling,MCMC,cosmology
Classifier: Development Status :: 5 - Production/Stable
Classifier: Operating System :: OS Independent
Classifier: Environment :: Console
Classifier: Intended Audience :: Science/Research
Classifier: Topic :: Scientific/Engineering :: Astronomy
Classifier: Programming Language :: Python :: 3.10
Classifier: Programming Language :: Python :: 3.11
Classifier: Programming Language :: Python :: 3.12
Classifier: Programming Language :: Python :: 3.13
Classifier: Programming Language :: Python :: 3.14
Requires-Python: >=3.10.0
License-File: LICENCE.txt
Requires-Dist: numpy>=1.17.0
Requires-Dist: scipy>=1.5
Requires-Dist: pandas>=1.0.1
Requires-Dist: PyYAML>=5.1
Requires-Dist: requests>=2.18
Requires-Dist: py-bobyqa>=1.4
Requires-Dist: GetDist>=1.3.1
Requires-Dist: fuzzywuzzy>=0.17
Requires-Dist: packaging>=24.2
Requires-Dist: tqdm
Requires-Dist: portalocker>=2.3.0
Requires-Dist: dill>=0.3.3
Requires-Dist: typing_extensions
Provides-Extra: speed
Requires-Dist: numba; extra == "speed"
Requires-Dist: mpi4py; extra == "speed"
Provides-Extra: gui
Requires-Dist: pyside6; extra == "gui"
Requires-Dist: matplotlib; extra == "gui"
Provides-Extra: docs
Requires-Dist: sphinx; extra == "docs"
Requires-Dist: sphinx_rtd_theme>=1.0; extra == "docs"
Requires-Dist: sphinxcontrib-jquery; extra == "docs"
Requires-Dist: sphinx-autodoc-typehints; extra == "docs"
Requires-Dist: sphinxcontrib-programoutput; extra == "docs"
Provides-Extra: devel
Requires-Dist: ruff; extra == "devel"
Requires-Dist: pre-commit; extra == "devel"
Requires-Dist: pyupgrade; extra == "devel"
Requires-Dist: pytest; extra == "devel"
Requires-Dist: pytest-xdist; extra == "devel"
Requires-Dist: pytest-cov; extra == "devel"
Requires-Dist: flaky; extra == "devel"
Requires-Dist: dill; extra == "devel"
Requires-Dist: mpi4py; extra == "devel"
Requires-Dist: iminuit; extra == "devel"
Dynamic: license-file
